bdtrans/__init__.py
bdtrans/_global.py
bdtrans/baidu.py
bdtrans/cmdline.py
bdtrans/deploy.py
bdtrans/error.py
bdtrans/language.py
bdtrans/lib.py
bdtrans/repl.py
bdtrans/locale/zh_CN/LC_MESSAGES/translate.mo
bdtrans-0.4.0.dist-info/METADATA
bdtrans-0.4.0.dist-info/RECORD
bdtrans-0.4.0.dist-info/WHEEL
bdtrans-0.4.0.dist-info/entry_points.txt
bdtrans-0.4.0.dist-info/top_level.txt
