Metadata-Version: 2.1
Name: bdtrans
Version: 0.4.0
Summary: A library for china baidu translation
Home-page: https://github.com/zsimline/bdtrans
Author: Mxsyx
Author-email: zsimline@163.com
License: GNU GENERAL PUBLIC LICENSE
Platform: any
Classifier: Programming Language :: Python :: 3
Classifier: License :: OSI Approved :: GNU General Public License (GPL)
Classifier: Operating System :: OS Independent
Requires-Dist: setuptools
Requires-Dist: prompt-toolkit
